{
	"parent": "item/handheld_rod",
	"textures": {
		"layer0": "item/carrot_on_a_stick"
	},
	"overrides": [
		{ "predicate": {"custom_model_data": 420001}, "model": "item/um/demon_head"},
		{ "predicate": {"custom_model_data": 420002}, "model": "item/um/demon_arm"},
		{ "predicate": {"custom_model_data": 420004}, "model": "item/um/ds_longsword_sheathed"},
		{ "predicate": {"custom_model_data": 420005}, "model": "item/um/ds_longsword"},
		{ "predicate": {"custom_model_data": 420006}, "model": "item/um/fire_orb"},
		{ "predicate": {"custom_model_data": 420020}, "model": "item/um/pit_lord_head"},
		{ "predicate": {"custom_model_data": 420033}, "model": "item/um/inspector"},
		{ "predicate": {"custom_model_data": 420035}, "model": "item/um/elemental_hand"},
		{ "predicate": {"custom_model_data": 420036}, "model": "item/um/elemental_head"},
		{ "predicate": {"custom_model_data": 420045}, "model": "item/um/blood_amalgam"},
		{ "predicate": {"custom_model_data": 420046}, "model": "item/um/blood_nodule"},
		{ "predicate": {"custom_model_data": 420051}, "model": "item/um/wither_bone"},
		{ "predicate": {"custom_model_data": 420052}, "model": "item/um/inferno_staff"},
		{ "predicate": {"custom_model_data": 420053}, "model": "item/um/blood_monolith_item"},
		{ "predicate": {"custom_model_data": 420054}, "model": "item/um/blood_monolith"},
		{ "predicate": {"custom_model_data": 420068}, "model": "item/um/shadow_longsword_sheathed"},
		{ "predicate": {"custom_model_data": 420069}, "model": "item/um/shadow_longsword"},
		{ "predicate": {"custom_model_data": 420072}, "model": "item/um/shadow_guardian"},
		{ "predicate": {"custom_model_data": 420073}, "model": "item/um/phantasmal_dagger"},
		{ "predicate": {"custom_model_data": 420074}, "model": "item/um/phantasmal_dagger_thrown"},
		{ "predicate": {"custom_model_data": 420075}, "model": "item/um/charm_swapping_sigil"},
		{ "predicate": {"custom_model_data": 420076}, "model": "item/um/elder_eye"},
		{ "predicate": {"custom_model_data": 420077}, "model": "item/um/elder_hand"},
		{ "predicate": {"custom_model_data": 420081}, "model": "item/um/elder_staff"},
		{ "predicate": {"custom_model_data": 420082}, "model": "item/um/shadebeast"},
		{ "predicate": {"custom_model_data": 420083}, "model": "item/um/shadebeast_alpha"},
		{ "predicate": {"custom_model_data": 420084}, "model": "item/um/salamander"},
		{ "predicate": {"custom_model_data": 420085}, "model": "item/um/locator_card"},
		{ "predicate": {"custom_model_data": 420086}, "model": "item/um/recall_locator_card"},
		{ "predicate": {"custom_model_data": 420087}, "model": "item/um/ender_wyrmling1"},
		{ "predicate": {"custom_model_data": 420088}, "model": "item/um/ender_wyrmling2"},
		{ "predicate": {"custom_model_data": 420089}, "model": "item/um/ender_wyrmling3"},
		{ "predicate": {"custom_model_data": 420090}, "model": "item/um/dragon_wings1"},
		{ "predicate": {"custom_model_data": 420091}, "model": "item/um/dragon_wings2"},
		{ "predicate": {"custom_model_data": 420092}, "model": "item/um/dragon_wings3"},
		{ "predicate": {"custom_model_data": 420093}, "model": "item/um/crown_of_ruin"},
		{ "predicate": {"custom_model_data": 420094}, "model": "item/um/voidling_head"},
		{ "predicate": {"custom_model_data": 420095}, "model": "item/um/voidling_hand"},
		{ "predicate": {"custom_model_data": 420096}, "model": "item/um/abyss_boss"},
		{ "predicate": {"custom_model_data": 420097}, "model": "item/um/iron_rod"},
		{ "predicate": {"custom_model_data": 420098}, "model": "item/um/diamond_piercer"},
		{ "predicate": {"custom_model_data": 420099}, "model": "item/um/prismatic_scepter"},
		{ "predicate": {"custom_model_data": 420100}, "model": "item/um/dragon_staff"},
		{ "predicate": {"custom_model_data": 420101}, "model": "item/um/demon_flame_scepter"},
		{ "predicate": {"custom_model_data": 420102}, "model": "item/um/blood_rain_staff_1"},
		{ "predicate": {"custom_model_data": 420103}, "model": "item/um/shadow_force_wand"},
		{ "predicate": {"custom_model_data": 420104}, "model": "item/um/oblivion_staff"},
		{ "predicate": {"custom_model_data": 420105}, "model": "item/um/blood_rain_staff_2"},
		{ "predicate": {"custom_model_data": 420106}, "model": "item/um/blood_rain_staff_3"},
		{ "predicate": {"custom_model_data": 420107}, "model": "item/um/logo"},
		{ "predicate": {"custom_model_data": 420108}, "model": "item/um/abyss_longsword_sheathed"},
		{ "predicate": {"custom_model_data": 420109}, "model": "item/um/abyss_longsword"},
		{ "predicate": {"custom_model_data": 420110}, "model": "item/um/mythical_dragon_egg"},
		{ "predicate": {"custom_model_data": 420111}, "model": "item/um/infernal_soulcrystal"},
		{ "predicate": {"custom_model_data": 420112}, "model": "item/um/bloody_idol"},
		{ "predicate": {"custom_model_data": 420113}, "model": "item/um/elder_wyrmling1"},
		{ "predicate": {"custom_model_data": 420114}, "model": "item/um/elder_wyrmling2"},
		{ "predicate": {"custom_model_data": 420115}, "model": "item/um/elder_wyrmling3"},
		{ "predicate": {"custom_model_data": 420116}, "model": "item/um/imp1"},
		{ "predicate": {"custom_model_data": 420117}, "model": "item/um/imp2"},
		{ "predicate": {"custom_model_data": 420118}, "model": "item/um/imp3"},
		{ "predicate": {"custom_model_data": 420119}, "model": "item/um/elder_imp1"},
		{ "predicate": {"custom_model_data": 420120}, "model": "item/um/elder_imp2"},
		{ "predicate": {"custom_model_data": 420121}, "model": "item/um/elder_imp3"},
		{ "predicate": {"custom_model_data": 420122}, "model": "item/um/abyssal_mirror"},
		{ "predicate": {"custom_model_data": 420123}, "model": "item/um/abyssal_revenant"},
		{ "predicate": {"custom_model_data": 420126}, "model": "item/um/doom_desire"},
		{ "predicate": {"custom_model_data": 420128}, "model": "item/um/pit_abs"},
		{ "predicate": {"custom_model_data": 420129}, "model": "item/um/disciple_of_destruction"},
		{ "predicate": {"custom_model_data": 420130}, "model": "item/um/disciple_of_death"},
		{ "predicate": {"custom_model_data": 420131}, "model": "item/um/spectral_sickle"}
	]
}
