{
  "pools": [
    {
      "rolls": 1,
      "entries": [
        {
          "type": "minecraft:item",
          "name": "minecraft:carrot_on_a_stick",
          "functions": [
            {
              "function": "minecraft:set_nbt",
              "tag": "{display:{Name:'{\"text\":\"Spectral Sickle\",\"color\":\"light_purple\",\"italic\":false}',Lore:['{\"text\":\"Fires scythe blades.\",\"color\":\"gray\",\"italic\":false}']},Unbreakable:1b,CustomModelData:420131,um_id:\"spectral_sickle\"}"
            }
          ]
        }
      ]
    },
    {
      "rolls": 1,
      "entries": [
        {
          "type": "minecraft:loot_table",
          "name": "undermagic:items/abyss_shard",
          "functions": [
            {
              "function": "minecraft:set_count",
              "count": {
                "min": 4,
                "max": 10
              }
            }
          ]
        }
      ]
    },
    {
      "rolls": 1,
      "entries": [{
        "type": "minecraft:loot_table",
        "name": "undermagic:charm_drop",
        "functions": [{
          "function": "minecraft:set_count",
          "count": 1
        }]
      }]
    }
  ]
}